Metadata-Version: 2.4
Name: fsl_sub
Version: 2.10.0
Summary: FSL Cluster Submission Script
Author-email: Duncan Mortimer <duncan.mortimer@ndcn.ox.ac.uk>
License: Apache License Version 2.0
Project-URL: Repository, https://git.fmrib.ox.ac.uk/fsl/fsl_sub/
Project-URL: Documentation, https://fsl.fmrib.ox.ac.uk/fsl/docs/#/utilities/fsl_sub
Classifier: Development Status :: 5 - Production/Stable
Classifier: Intended Audience :: Science/Research
Classifier: Topic :: Scientific/Engineering :: Medical Science Apps.
Classifier: License :: OSI Approved :: Apache Software License
Classifier: Programming Language :: Python :: 3.9
Classifier: Programming Language :: Python :: 3.10
Classifier: Programming Language :: Python :: 3.11
Classifier: Programming Language :: Python :: 3.12
Classifier: Programming Language :: Python :: 3.13
Classifier: Topic :: Software Development :: Libraries :: Python Modules
Classifier: Natural Language :: English
Classifier: Environment :: Console
Classifier: Operating System :: MacOS :: MacOS X
Classifier: Operating System :: POSIX :: Linux
Requires-Python: >=3.8
License-File: LICENSE
Requires-Dist: ruamel.yaml>=0.16.7
Provides-Extra: test
Requires-Dist: pytest; extra == "test"
Requires-Dist: pytest-mock; extra == "test"
Requires-Dist: coverage; extra == "test"
Requires-Dist: pytest-cov; extra == "test"
Requires-Dist: tomli; python_version < "3.12" and extra == "test"
Provides-Extra: style
Requires-Dist: pylint; extra == "style"
Requires-Dist: flake8; extra == "style"
Dynamic: license-file
